AUTHORS.md
CHANGELOG.md
LICENSE
README.md
pyproject.toml
example/README.md
places/__init__.py
places/apps.py
places/conf.py
places/fields.py
places/forms.py
places/models.py
places/widgets.py
places/static/places/places.css
places/static/places/places.js
places/templates/places/widgets/places.html
dj_places-5.2.1.dist-info/METADATA
dj_places-5.2.1.dist-info/WHEEL
dj_places-5.2.1.dist-info/licenses/AUTHORS.md
dj_places-5.2.1.dist-info/licenses/LICENSE
dj_places-5.2.1.dist-info/RECORD
