Metadata-Version: 2.1
Name: dj-places
Version: 5.2.1
Summary: A django app for store places using Google Maps API
Project-URL: Funding, https://donate.pypi.org
Project-URL: Homepage, http://oscarmcm.github.io/django-places/
Project-URL: Source, https://github.com/oscarmcm/django-places/
Project-URL: Tracker, https://github.com/oscarmcm/django-places/issues
Author-email: Oscar Cortez <om.cortez.2010@gmail.com>
License-Expression: MIT
License-File: AUTHORS.md
License-File: LICENSE
Keywords: django,geocomplete,google,maps,places
Classifier: Development Status :: 5 - Production/Stable
Classifier: Environment :: Web Environment
Classifier: Framework :: Django
Classifier: Intended Audience :: Developers
Classifier: License :: OSI Approved :: BSD License
Classifier: Natural Language :: English
Classifier: Operating System :: OS Independent
Classifier: Programming Language :: Python
Classifier: Programming Language :: Python :: 3
Requires-Python: >=3.6
Requires-Dist: django>=3.0
